sagemaker/__init__.py
sagemaker/mlops/__init__.py
sagemaker/mlops/local/__init__.py
sagemaker/mlops/local/exceptions.py
sagemaker/mlops/local/local_pipeline_session.py
sagemaker/mlops/local/pipeline.py
sagemaker/mlops/local/pipeline_entities.py
sagemaker/mlops/workflow/__init__.py
sagemaker/mlops/workflow/_event_bridge_client_helper.py
sagemaker/mlops/workflow/_repack_model.py
sagemaker/mlops/workflow/_steps_compiler.py
sagemaker/mlops/workflow/_utils.py
sagemaker/mlops/workflow/automl_step.py
sagemaker/mlops/workflow/callback_step.py
sagemaker/mlops/workflow/check_job_config.py
sagemaker/mlops/workflow/clarify_check_step.py
sagemaker/mlops/workflow/condition_step.py
sagemaker/mlops/workflow/emr_step.py
sagemaker/mlops/workflow/fail_step.py
sagemaker/mlops/workflow/function_step.py
sagemaker/mlops/workflow/lambda_step.py
sagemaker/mlops/workflow/model_step.py
sagemaker/mlops/workflow/monitor_batch_transform_step.py
sagemaker/mlops/workflow/notebook_job_step.py
sagemaker/mlops/workflow/parallelism_config.py
sagemaker/mlops/workflow/pipeline.py
sagemaker/mlops/workflow/pipeline_experiment_config.py
sagemaker/mlops/workflow/quality_check_step.py
sagemaker/mlops/workflow/retry.py
sagemaker/mlops/workflow/selective_execution_config.py
sagemaker/mlops/workflow/step_collections.py
sagemaker/mlops/workflow/steps.py
sagemaker/mlops/workflow/triggers.py
sagemaker_mlops-1.3.1.dist-info/METADATA
sagemaker_mlops-1.3.1.dist-info/WHEEL
sagemaker_mlops-1.3.1.dist-info/top_level.txt
sagemaker_mlops-1.3.1.dist-info/RECORD
