Metadata-Version: 2.4
Name: sagemaker-mlops
Version: 1.3.1
Summary: SageMaker MLOps package for workflow orchestration and model building
Author: Amazon Web Services
Classifier: Development Status :: 3 - Alpha
Classifier: Intended Audience :: Developers
Classifier: License :: OSI Approved :: Apache Software License
Classifier: Programming Language :: Python :: 3
Classifier: Programming Language :: Python :: 3.9
Classifier: Programming Language :: Python :: 3.10
Classifier: Programming Language :: Python :: 3.11
Classifier: Programming Language :: Python :: 3.12
Requires-Python: >=3.9
Requires-Dist: sagemaker-core>=2.3.1
Requires-Dist: sagemaker-train>=1.3.1
Requires-Dist: sagemaker-serve>=1.3.1
Requires-Dist: boto3<2.0,>=1.42.2
Requires-Dist: botocore<2.0,>=1.42.2
Provides-Extra: test
Requires-Dist: pytest; extra == "test"
Requires-Dist: pytest-cov; extra == "test"
Requires-Dist: mock; extra == "test"
Provides-Extra: dev
Requires-Dist: pytest; extra == "dev"
Requires-Dist: pytest-cov; extra == "dev"
Requires-Dist: mock; extra == "dev"
Requires-Dist: black; extra == "dev"
Requires-Dist: flake8; extra == "dev"
